<?xml version="1.0" encoding="utf-8"?>
<Message_Container_StatusUpdate_Storage_Arrival xmlns:xsi="http://www.w3.org/2001/XMLSchema-instance" xmlns:xsd="http://www.w3.org/2001/XMLSchema">
  <MessageHeaderInfo>
    <OTFVersion>OTF22</OTFVersion>
    <OTFMessage>Message_Container_StatusUpdate_Storage_Arrival</OTFMessage>
    <MessageID>DummyString</MessageID>
    <ConversationID>DummyString</ConversationID>
    <SenderID>DummyString</SenderID>
    <RecipientID>DummyString</RecipientID>
    <ContactInfo>
      <Name>DummyString</Name>
      <ExternalID>DummyString</ExternalID>
      <Phone>DummyString</Phone>
      <Email>DummyString</Email>
    </ContactInfo>
    <SentDate>2023-09-22T13:17:00.3051124+02:00</SentDate>
    <MessageType>New</MessageType>
  </MessageHeaderInfo>
  <OrderInfo>
    <SupplierID>DummyString</SupplierID>
    <SupplierFacilityID>DummyString</SupplierFacilityID>
    <SupplierBICFacilityCode>DummyString</SupplierBICFacilityCode>
    <SupplierProformaReference>DummyString</SupplierProformaReference>
    <SupplierOrderReference>DummyString</SupplierOrderReference>
    <OrderStatusInfo>
      <OrderStatus>UNKNOWN</OrderStatus>
      <OrderStatusDescription>DummyString</OrderStatusDescription>
    </OrderStatusInfo>
    <ClientID>DummyString</ClientID>
    <ClientFacilityID>DummyString</ClientFacilityID>
    <ClientBICFacilityCode>DummyString</ClientBICFacilityCode>
    <ClientOrderReference>DummyString</ClientOrderReference>
  </OrderInfo>
  <ContainerInfo>
    <ContainerNumber>DummyString</ContainerNumber>
    <ContainerType>DummyString</ContainerType>
  </ContainerInfo>
  <Container_StatusUpdate_Storage_Arrival>
    <ClientPurchaseOrderReference>DummyString</ClientPurchaseOrderReference>
    <ClientDeliveryReference>DummyString</ClientDeliveryReference>
    <ContainerDeliveryDate>2023-09-22T13:17:00.3051286+02:00</ContainerDeliveryDate>
    <Container_HaulierInfo>
      <HaulierName>DummyString</HaulierName>
      <TruckDriverName>DummyString</TruckDriverName>
      <TruckLicensePlate>DummyString</TruckLicensePlate>
      <ChassisLicensePlate>DummyString</ChassisLicensePlate>
    </Container_HaulierInfo>
  </Container_StatusUpdate_Storage_Arrival>
  <Remarks>
    <Remark>
      <RemarkID>DummyString</RemarkID>
      <RemarkDate>2023-09-22T13:17:00.3051359+02:00</RemarkDate>
      <RemarkAuthor>DummyString</RemarkAuthor>
      <RemarkText>DummyString</RemarkText>
    </Remark>
    <Remark>
      <RemarkID>DummyString</RemarkID>
      <RemarkDate>2023-09-22T13:17:00.3051379+02:00</RemarkDate>
      <RemarkAuthor>DummyString</RemarkAuthor>
      <RemarkText>DummyString</RemarkText>
    </Remark>
  </Remarks>
  <Attachments>
    <Attachment>
      <Name>DummyString</Name>
      <URL>DummyString</URL>
      <ExternalID>DummyString</ExternalID>
      <Tags>
        <Tag>DummyString</Tag>
      </Tags>
      <Tags>
        <Tag>DummyString</Tag>
      </Tags>
    </Attachment>
    <Attachment>
      <Name>DummyString</Name>
      <URL>DummyString</URL>
      <ExternalID>DummyString</ExternalID>
      <Tags>
        <Tag>DummyString</Tag>
      </Tags>
      <Tags>
        <Tag>DummyString</Tag>
      </Tags>
    </Attachment>
  </Attachments>
</Message_Container_StatusUpdate_Storage_Arrival>